{
    "walking": 935,
    "going": 558,
    "moving": 519,
    "walks": 516,
    "turns": 499,
    "coming": 364,
    "looks": 324,
    "entering": 294,
    "moves": 205,
    "looking": 194,
    "left": 176,
    "disappears": 141,
    "standing": 139,
    "heading": 138,
    "starts": 135,
    "stops": 130,
    "stands": 126,
    "running": 116,
    "using": 106,
    "exits": 100,
    "takes": 98,
    "eating": 97,
    "jumps": 93,
    "runs": 91,
    "exiting": 89,
    "swimming": 88,
    "remains": 87,
    "approaching": 79,
    "swims": 77,
    "begins": 70,
    "goes": 69,
    "fighting": 65,
    "adjusting": 64,
    "enters": 64,
    "gets": 64,
    "holding": 62,
    "pointing": 62,
    "raises": 59,
    "faces": 57,
    "appears": 55,
    "keeping": 53,
    "falls": 52,
    "turning": 52,
    "talking": 51,
    "makes": 51,
    "sits": 50,
    "comes": 49,
    "touching": 48,
    "shifting": 47,
    "walk": 46,
    "jumping": 44,
    "making": 44,
    "pushes": 44,
    "pushed": 43,
    "leaving": 43,
    "glances": 42,
    "sitting": 41,
    "crossing": 41,
    "passes": 40,
    "attacking": 39,
    "seated": 38,
    "facing": 37,
    "climbs": 37,
    "trying": 35,
    "slows": 34,
    "playing": 34,
    "riding": 32,
    "carrying": 32,
    "approaches": 32,
    "pauses": 31,
    "eats": 31,
    "puts": 31,
    "wearing": 29,
    "crosses": 29,
    "flying": 28,
    "move": 28,
    "pushing": 27,
    "halts": 27,
    "gazes": 26,
    "falling": 26,
    "lowers": 25,
    "lifts": 25,
    "hops": 24,
    "parked": 24,
    "fixing": 24,
    "getting": 24,
    "show": 23,
    "lying": 23,
    "rises": 22,
    "searching": 22,
    "attacked": 22,
    "overtakes": 21,
    "places": 21,
    "taking": 20,
    "stays": 20,
    "face": 19,
    "descends": 19,
    "cross": 19,
    "sniffing": 18,
    "racing": 17,
    "reaches": 17,
    "leaps": 17,
    "drinking": 17,
    "grabs": 17,
    "rotates": 17,
    "rolls": 16,
    "throws": 16,
    "engages": 16,
    "indicate": 16,
    "steps": 16,
    "resting": 16,
    "waiting": 15,
    "climbing": 15,
    "bites": 15,
    "vanishes": 15,
    "brings": 15,
    "giving": 15,
    "straightens": 15,
    "adjusts": 14,
    "leans": 14,
    "attack": 14,
    "flies": 14,
    "circling": 14,
    "engaged": 14,
    "has": 14,
    "attempting": 13,
    "asserting": 13,
    "descending": 13,
    "bends": 13,
    "emerges": 13,
    "changes": 13,
    "talks": 12,
    "dominated": 12,
    "rides": 12,
    "drops": 12,
    "touches": 12,
    "disturbed": 12,
    "pulls": 12,
    "positions": 12,
    "watching": 12,
    "run": 12,
    "conversing": 11,
    "grazing": 11,
    "gazing": 11,
    "traveling": 11,
    "picking": 11,
    "drives": 10,
    "disturbing": 10,
    "follows": 10,
    "staying": 10,
    "remaining": 10,
    "flaps": 10,
    "go": 10,
    "removes": 10,
    "chasing": 10,
    "placing": 10,
    "talk": 10,
    "look": 9,
    "turing": 9,
    "positioned": 9,
    "tilts": 9,
    "enter": 9,
    "bite": 8,
    "carries": 8,
    "inspects": 8,
    "hoop": 8,
    "holds": 8,
    "passing": 8,
    "shifts": 8,
    "attacks": 8,
    "showing": 8,
    "consuming": 8,
    "turn": 8,
    "lies": 8,
    "receiving": 8,
    "feeding": 8,
    "kicks": 8,
    "nudges": 8,
    "get": 8,
    "avoid": 8,
    "following": 8,
    "advancing": 7,
    "hitting": 7,
    "returning": 7,
    "ascends": 7,
    "glancing": 7,
    "headbutts": 7,
    "joining": 7,
    "chases": 7,
    "followed": 7,
    "kick": 7,
    "crashing": 7,
    "examines": 7,
    "balance": 7,
    "rests": 7,
    "leaves": 7,
    "picks": 7,
    "head": 7,
    "ceases": 7,
    "gains": 6,
    "taken": 6,
    "lands": 6,
    "stopped": 6,
    "spins": 6,
    "covers": 6,
    "hold": 6,
    "take": 6,
    "refrains": 6,
    "dancing": 6,
    "blocked": 6,
    "speaking": 6,
    "travels": 6,
    "heads": 6,
    "twists": 6,
    "biting": 6,
    "scratches": 6,
    "carried": 5,
    "attempts": 5,
    "push": 5,
    "collides": 5,
    "checking": 5,
    "eat": 5,
    "maneuvering": 5,
    "perched": 5,
    "speeds": 5,
    "completes": 5,
    "guide": 5,
    "overpowered": 5,
    "proceeds": 5,
    "lays": 5,
    "nears": 5,
    "doing": 5,
    "approach": 5,
    "emerging": 5,
    "direct": 5,
    "point": 5,
    "lifting": 5,
    "catch": 5,
    "checks": 5,
    "refraining": 5,
    "chased": 5,
    "having": 5,
    "ducks": 5,
    "drive": 5,
    "clapping": 5,
    "driving": 5,
    "escapes": 5,
    "pecks": 5,
    "covered": 5,
    "bothering": 5,
    "asking": 5,
    "filled": 5,
    "containing": 4,
    "continues": 4,
    "fights": 4,
    "kicking": 4,
    "converses": 4,
    "drink": 4,
    "drinks": 4,
    "reduces": 4,
    "meeting": 4,
    "navigates": 4,
    "alters": 4,
    "shakes": 4,
    "hit": 4,
    "stand": 4,
    "waits": 4,
    "rotating": 4,
    "maintaining": 4,
    "arranging": 4,
    "landing": 4,
    "came": 4,
    "leading": 4,
    "fixed": 4,
    "thrown": 4,
    "stretches": 4,
    "chatting": 4,
    "swim": 4,
    "observes": 4,
    "blocking": 4,
    "perches": 4,
    "peeking": 4,
    "taps": 4,
    "points": 4,
    "transferring": 4,
    "turned": 4,
    "colliding": 4,
    "pecking": 4,
    "recording": 4,
    "dragging": 4,
    "keeps": 4,
    "flips": 4,
    "pins": 4,
    "extending": 4,
    "leaping": 4,
    "feeds": 4,
    "chats": 4,
    "visiting": 4,
    "switches": 4,
    "stretching": 4,
    "providing": 4,
    "slides": 4,
    "resumes": 4,
    "tumbles": 4,
    "retracts": 4,
    "slips": 4,
    "uses": 4,
    "inspecting": 4,
    "obstructed": 4,
    "participating": 4,
    "scratching": 4,
    "changing": 4,
    "abstaining": 4,
    "slowing": 3,
    "working": 3,
    "nibbling": 3,
    "lifted": 3,
    "sticks": 3,
    "plays": 3,
    "battling": 3,
    "circles": 3,
    "returns": 3,
    "bending": 3,
    "pulling": 3,
    "rowing": 3,
    "reclining": 3,
    "catches": 3,
    "pecked": 3,
    "fixes": 3,
    "stopping": 3,
    "leaning": 3,
    "controlling": 3,
    "leave": 3,
    "peeing": 3,
    "gives": 3,
    "tumbling": 3,
    "tries": 3,
    "bear": 3,
    "engaging": 3,
    "gossiping": 3,
    "galloping": 3,
    "raising": 3,
    "executing": 3,
    "climb": 3,
    "videotaping": 3,
    "arriving": 3,
    "ascending": 3,
    "rolled": 3,
    "cycling": 3,
    "moved": 3,
    "park": 3,
    "start": 3,
    "watches": 3,
    "knocks": 3,
    "splashing": 3,
    "speaks": 3,
    "clasps": 3,
    "obscured": 3,
    "speeding": 3,
    "signal": 3,
    "pulled": 3,
    "avoiding": 3,
    "rubbing": 3,
    "touch": 3,
    "advances": 3,
    "records": 3,
    "fall": 3,
    "accessing": 3,
    "avoided": 3,
    "retraces": 2,
    "hands": 2,
    "asserts": 2,
    "converse": 2,
    "Goat": 2,
    "pinned": 2,
    "displaying": 2,
    "lanes": 2,
    "yawns": 2,
    "departing": 2,
    "situated": 2,
    "assembling": 2,
    "draws": 2,
    "navigating": 2,
    "examining": 2,
    "leaned": 2,
    "disappearing": 2,
    "cuddling": 2,
    "inclines": 2,
    "investigating": 2,
    "stop": 2,
    "peck": 2,
    "pausing": 2,
    "stepping": 2,
    "paces": 2,
    "preparing": 2,
    "seating": 2,
    "maintains": 2,
    "nudging": 2,
    "consumes": 2,
    "tosses": 2,
    "pause": 2,
    "held": 2,
    "switching": 2,
    "flapping": 2,
    "hanging": 2,
    "films": 2,
    "decreasing": 2,
    "catching": 2,
    "foraging": 2,
    "embraces": 2,
    "retract": 2,
    "nods": 2,
    "sprinting": 2,
    "pivots": 2,
    "proceeding": 2,
    "kicked": 2,
    "petting": 2,
    "rolling": 2,
    "docked": 2,
    "control": 2,
    "plucking": 2,
    "arrived": 2,
    "fades": 2,
    "struck": 2,
    "searches": 2,
    "releases": 2,
    "buying": 2,
    "clasped": 2,
    "compared": 2,
    "spreading": 2,
    "sings": 2,
    "bringing": 2,
    "shaking": 2,
    "pedaling": 2,
    "parks": 2,
    "speak": 2,
    "collapses": 2,
    "offered": 2,
    "injured": 2,
    "observing": 2,
    "hangs": 2,
    "carry": 2,
    "covering": 2,
    "peeling": 2,
    "attaches": 2,
    "controlled": 2,
    "calls": 2,
    "waves": 2,
    "sprint": 2,
    "put": 2,
    "gathering": 2,
    "tailgate": 2,
    "nudge": 2,
    "give": 2,
    "transfers": 2,
    "reducing": 2,
    "causing": 2,
    "pursues": 2,
    "connecting": 2,
    "affected": 2,
    "retreats": 2,
    "laid": 2,
    "gliding": 2,
    "smoking": 2,
    "grasps": 2,
    "licks": 2,
    "forced": 2,
    "fed": 2,
    "chews": 2,
    "forcing": 2,
    "arrive": 2,
    "adjust": 2,
    "accelerates": 2,
    "frees": 2,
    "soaring": 2,
    "strolling": 2,
    "hand": 2,
    "extends": 2,
    "support": 2,
    "flipped": 2,
    "released": 2,
    "anchored": 2,
    "obstructs": 2,
    "crawls": 2,
    "fight": 2,
    "displayed": 2,
    "hugs": 2,
    "lowered": 2,
    "carriage": 2,
    "becomes": 2,
    "bumping": 2,
    "waving": 2,
    "striking": 2,
    "struggles": 2,
    "dragged": 2,
    "rows": 2,
    "tossed": 2,
    "slipping": 2,
    "overtaking": 1,
    "tracks": 1,
    "leads": 1,
    "bumped": 1,
    "ask": 1,
    "disturbs": 1,
    "retreating": 1,
    "dismounts": 1,
    "seizes": 1,
    "decelerating": 1,
    "brought": 1,
    "help": 1,
    "return": 1,
    "contains": 1,
    "punch": 1,
    "traversing": 1,
    "dashes": 1,
    "paddling": 1,
    "sharing": 1,
    "assaults": 1,
    "cycles": 1,
    "sipping": 1,
    "initiates": 1,
    "refusing": 1,
    "straying": 1,
    "shore": 1,
    "front": 1,
    "trails": 1,
    "demonstrating": 1,
    "discards": 1,
    "stuck": 1,
    "set": 1,
    "worn": 1,
    "grooms": 1,
    "touche": 1,
    "jumped": 1,
    "pursue": 1,
    "snatches": 1,
    "swings": 1,
    "lagging": 1,
    "ground": 1,
    "spinning": 1,
    "beginning": 1,
    "disappeared": 1,
    "hop": 1,
    "skid": 1,
    "positioning": 1,
    "opens": 1,
    "distancing": 1,
    "hugging": 1,
    "bows": 1,
    "tail": 1,
    "sways": 1,
    "decelerates": 1,
    "submerged": 1,
    "staring": 1,
    "transitioning": 1,
    "peaks": 1,
    "scans": 1,
    "placed": 1,
    "becoming": 1,
    "attempted": 1,
    "bobbing": 1,
    "removed": 1,
    "peels": 1,
    "chewing": 1,
    "offering": 1,
    "slowed": 1,
    "wears": 1,
    "touched": 1,
    "reclines": 1,
    "clicks": 1,
    "progressing": 1,
    "avoids": 1,
    "putting": 1,
    "inserts": 1,
    "disturb": 1,
    "embracing": 1,
    "depart": 1,
    "jerks": 1,
    "handle": 1,
    "bother": 1,
    "munching": 1,
    "check": 1,
    "removing": 1,
    "tracking": 1,
    "practices": 1,
    "rose": 1,
    "presses": 1,
    "manage": 1,
    "log": 1,
    "tilting": 1,
    "ascend": 1,
    "reaching": 1,
    "nudged": 1,
    "urinating": 1,
    "straightening": 1,
    "grab": 1,
    "designated": 1,
    "punching": 1,
    "reappears": 1,
    "tied": 1,
    "fly": 1,
    "hits": 1,
    "scratch": 1,
    "backwards": 1,
    "crouches": 1,
    "aligns": 1,
    "interacting": 1,
    "ling": 1,
    "deviating": 1,
    "make": 1,
    "stumbles": 1,
    "revolving": 1,
    "patting": 1,
    "preens": 1,
    "bikes": 1,
    "escape": 1,
    "maintain": 1,
    "delivers": 1,
    "reversing": 1,
    "seen": 1,
    "draped": 1,
    "races": 1,
    "sails": 1,
    "supporting": 1,
    "come": 1,
    "surveys": 1,
    "assaulted": 1,
    "bothered": 1,
    "lied": 1,
    "stumbling": 1,
    "assist": 1,
    "practicing": 1,
    "reach": 1,
    "protect": 1,
    "settles": 1,
    "straps": 1,
    "signaling": 1,
    "relocated": 1,
    "sideways": 1,
    "shows": 1,
    "munches": 1,
    "land": 1,
    "goat": 1,
    "vaults": 1,
    "emits": 1,
    "smoke": 1,
    "spreads": 1,
    "interacts": 1,
    "pursued": 1,
    "decreases": 1,
    "scaling": 1,
    "halted": 1,
    "secured": 1,
    "strikes": 1,
    "fallen": 1,
    "flipping": 1,
    "lowering": 1,
    "scurries": 1,
    "shield": 1,
    "pressing": 1,
    "hug": 1,
    "trailing": 1,
    "rearranges": 1,
    "handing": 1,
    "rising": 1,
    "located": 1,
    "opening": 1,
    "keep": 1,
    "indicates": 1,
    "indicating": 1,
    "balances": 1,
    "widens": 1,
    "right": 1,
    "exit": 1,
    "dropping": 1,
    "chase": 1,
    "reverses": 1,
    "starting": 1,
    "accompanied": 1,
    "flees": 1,
    "preventing": 1,
    "drags": 1,
    "retaliates": 1,
    "boards": 1,
    "pokes": 1,
    "retrieves": 1,
    "strolls": 1,
    "hides": 1,
    "choosing": 1,
    "engage": 1,
    "obstructing": 1,
    "veers": 1,
    "shoved": 1,
    "save": 1,
    "elevates": 1,
    "sinks": 1,
    "commences": 1,
    "hidden": 1,
    "bumps": 1,
    "chat": 1,
    "wading": 1,
    "dressed": 1,
    "steers": 1,
    "perching": 1,
    "throwing": 1,
    "retaliating": 1,
    "headed": 1,
    "slip": 1,
    "sends": 1,
    "pouncing": 1,
    "steering": 1,
    "entered": 1,
    "green": 1,
    "tugging": 1,
    "secures": 1,
    "blocks": 1,
    "shopping": 1
}